netbox_proxmox_import/__init__.py
netbox_proxmox_import/forms.py
netbox_proxmox_import/models.py
netbox_proxmox_import/navigation.py
netbox_proxmox_import/tables.py
netbox_proxmox_import/urls.py
netbox_proxmox_import/views.py
netbox_proxmox_import/api/__init__.py
netbox_proxmox_import/api/serializers.py
netbox_proxmox_import/api/sync.py
netbox_proxmox_import/api/urls.py
netbox_proxmox_import/api/views.py
netbox_proxmox_import/api/netbox/__init__.py
netbox_proxmox_import/api/netbox/categorizer.py
netbox_proxmox_import/api/netbox/parser.py
netbox_proxmox_import/api/netbox/updater.py
netbox_proxmox_import/api/proxmox/__init__.py
netbox_proxmox_import/api/proxmox/connector.py
netbox_proxmox_import/migrations/0001_initial.py
netbox_proxmox_import/migrations/__init__.py
netbox_proxmox_import/templates/netbox_proxmox_import/__init__.py
netbox_proxmox_import/templates/netbox_proxmox_import/management_panel.html
netbox_proxmox_import/templates/netbox_proxmox_import/proxmoxconnection.html
netbox_proxmox_import-1.1.2.dist-info/METADATA
netbox_proxmox_import-1.1.2.dist-info/WHEEL
netbox_proxmox_import-1.1.2.dist-info/top_level.txt
netbox_proxmox_import-1.1.2.dist-info/RECORD
